{
  "1": {
    "inputs": {
      "ckpt_name": "juggernautXL_juggXIByRundiffusion.safetensors"
    },
    "class_type": "CheckpointLoaderSimple",
    "_meta": {
      "title": "base_model"
    }
  },
  "3": {
    "inputs": {
      "text": "",
      "clip": [
        "1",
        1
      ]
    },
    "class_type": "CLIPTextEncode",
    "_meta": {
      "title": "prompt"
    }
  },
  "4": {
    "inputs": {
      "text": "",
      "clip": [
        "1",
        1
      ]
    },
    "class_type": "CLIPTextEncode",
    "_meta": {
      "title": "negative_prompt"
    }
  },
  "5": {
    "inputs": {
      "seed": 555803607816172,
      "steps": 30,
      "cfg": 6,
      "sampler_name": "euler_ancestral",
      "scheduler": "normal",
      "denoise": 1,
      "model": [
        "49",
        0
      ],
      "positive": [
        "3",
        0
      ],
      "negative": [
        "4",
        0
      ],
      "latent_image": [
        "6",
        0
      ]
    },
    "class_type": "KSampler",
    "_meta": {
      "title": "main_sampler"
    }
  },
  "6": {
    "inputs": {
      "width": 768,
      "height": 1344,
      "batch_size": 1
    },
    "class_type": "EmptyLatentImage",
    "_meta": {
      "title": "aspect_ratios_size"
    }
  },
  "7": {
    "inputs": {
      "samples": [
        "5",
        0
      ],
      "vae": [
        "52",
        0
      ]
    },
    "class_type": "VAEDecode",
    "_meta": {
      "title": "VAE Decode"
    }
  },
  "12": {
    "inputs": {
      "lora_name": "sd_xl_offset_example-lora_1.0.safetensors",
      "strength_model": 0,
      "model": [
        "1",
        0
      ]
    },
    "class_type": "LoraLoaderModelOnly",
    "_meta": {
      "title": "lora_1"
    }
  },
  "13": {
    "inputs": {
      "lora_name": "sd_xl_offset_example-lora_1.0.safetensors",
      "strength_model": 0,
      "model": [
        "12",
        0
      ]
    },
    "class_type": "LoraLoaderModelOnly",
    "_meta": {
      "title": "lora_2"
    }
  },
  "14": {
    "inputs": {
      "lora_name": "sd_xl_offset_example-lora_1.0.safetensors",
      "strength_model": 0,
      "model": [
        "13",
        0
      ]
    },
    "class_type": "LoraLoaderModelOnly",
    "_meta": {
      "title": "lora_3"
    }
  },
  "15": {
    "inputs": {
      "lora_name": "sd_xl_offset_example-lora_1.0.safetensors",
      "strength_model": 0,
      "model": [
        "14",
        0
      ]
    },
    "class_type": "LoraLoaderModelOnly",
    "_meta": {
      "title": "lora_4"
    }
  },
  "16": {
    "inputs": {
      "lora_name": "sd_xl_offset_example-lora_1.0.safetensors",
      "strength_model": 0,
      "model": [
        "15",
        0
      ]
    },
    "class_type": "LoraLoaderModelOnly",
    "_meta": {
      "title": "lora_5"
    }
  },
  "17": {
    "inputs": {
      "multiplier": 0.7,
      "model": [
        "18",
        0
      ]
    },
    "class_type": "RescaleCFG",
    "_meta": {
      "title": "RescaleCFG"
    }
  },
  "18": {
    "inputs": {
      "object_to_patch": "diffusion_model",
      "residual_diff_threshold": [
        "19",
        0
      ],
      "start": 0.2,
      "end": 0.9,
      "max_consecutive_cache_hits": 2,
      "model": [
        "16",
        0
      ]
    },
    "class_type": "ApplyFBCacheOnModel",
    "_meta": {
      "title": "Apply First Block Cache"
    }
  },
  "19": {
    "inputs": {
      "value": 0
    },
    "class_type": "easy float",
    "_meta": {
      "title": "wavespeed_strength"
    }
  },
  "41": {
    "inputs": {
      "check_mode": "any_vpred",
      "specific_type": "V_PREDICTION",
      "model": [
        "1",
        0
      ]
    },
    "class_type": "CheckVpredictionNode",
    "_meta": {
      "title": "Advanced V-Prediction Checker"
    }
  },
  "49": {
    "inputs": {
      "boolean": [
        "41",
        0
      ],
      "on_true": [
        "17",
        0
      ],
      "on_false": [
        "18",
        0
      ]
    },
    "class_type": "easy ifElse",
    "_meta": {
      "title": "If else"
    }
  },
  "51": {
    "inputs": {
      "images": [
        "7",
        0
      ]
    },
    "class_type": "SaveImageWebsocket",
    "_meta": {
      "title": "SaveImageWebsocket"
    }
  },
  "52": {
    "inputs": {
      "boolean": false,
      "on_true": [
        "53",
        0
      ],
      "on_false": [
        "1",
        2
      ]
    },
    "class_type": "easy ifElse",
    "_meta": {
      "title": "is_custom_vae"
    }
  },
  "53": {
    "inputs": {
      "vae_name": "ponyDiffusionV6XL_vae.safetensors"
    },
    "class_type": "VAELoader",
    "_meta": {
      "title": "Load VAE"
    }
  }
}